whisperx_karaoke/__init__.py
whisperx_karaoke/__main__.py
whisperx_karaoke/ass.py
whisperx_karaoke/cli.py
whisperx_karaoke/resolver.py
whisperx_karaoke-0.1.1.dist-info/METADATA
whisperx_karaoke-0.1.1.dist-info/WHEEL
whisperx_karaoke-0.1.1.dist-info/entry_points.txt
whisperx_karaoke-0.1.1.dist-info/top_level.txt
whisperx_karaoke-0.1.1.dist-info/RECORD
