Metadata-Version: 2.1
Name: whisperx-karaoke
Version: 0.1.1
Author: Darwin
License: MIT
Requires-Python: >=3.10
Requires-Dist: whisperx
